advancedLogger/__init__.py
advancedLogger/_handler.py
advancedLogger/_conf/__init__.py
advancedLogger/_els_logger/__init__.py
advancedLogger/_els_logger/_els_handler.py
advancedLogger/_els_logger/_els_logger.py
advancedLogger/_els_logger/_conf/__init__.py
advancedLogger/_els_logger/_conf/elasticsearch_conf.py
advancedLogger/_els_logger/_formatter/__init__.py
advancedLogger/_els_logger/_formatter/_els_formatter.py
advancedLogger/_els_logger/_index/__init__.py
advancedLogger/_els_logger/_index/_index_formatter.py
advancedLogger/_file_logger/__init__.py
advancedLogger/_formatter/__init__.py
advancedLogger/_formatter/_fmt_conf.py
advancedLogger/_formatter/_formatter.py
advancedLogger/_formatter/_http_formatter/__init__.py
advancedLogger/_formatter/_http_formatter/_http_request_type.py
advancedLogger/_formatter/_json_formatter/__init__.py
advancedLogger/_requests_logger/__init__.py
advancedLogger/_time/__init__.py
advancedLogger/_time/_time_formatter.py
advancedLogger/contract/__init__.py
advancedLogger/contract/els_index/IIndexFormatter.py
advancedLogger/contract/els_index/__init__.py
advancedLogger/contract/time/ITimeFormatter.py
advancedLogger/contract/time/__init__.py
advancedLogger/helpers/__init__.py
advancedLogger/helpers/_time.py
python_advanced_logger-0.1.2.dist-info/LICENSE.txt
python_advanced_logger-0.1.2.dist-info/METADATA
python_advanced_logger-0.1.2.dist-info/WHEEL
python_advanced_logger-0.1.2.dist-info/top_level.txt
python_advanced_logger-0.1.2.dist-info/RECORD
