Metadata-Version: 2.1
Name: python-advanced-logger
Version: 0.1.2
Summary: advanced python logging tools contains elasticsearch and file logger
Home-page: https://github.com/MatinKarbasioun/PythonAdvancedLogger/
Author: Matin Karbasioun
Author-email: matinkarbasioun@gmail.com
Project-URL: Bug Tracker, https://github.com/MatinKarbasioun/PythonAdvancedLogger/issues
Classifier: Programming Language :: Python :: 3.11
Classifier: License :: OSI Approved :: MIT License
Classifier: Operating System :: OS Independent
Requires-Python: >=3.10
License-File: LICENSE.txt
Requires-Dist: elasticsearch (==7.17.8)
Requires-Dist: pytz (>=2022.7)
Requires-Dist: requests (>=2.28.1)
Requires-Dist: tzdata (==2022.7)
Requires-Dist: urllib3 (==1.26.13)
